gradle.properties
hexdoc_hyperhexcast/__gradle_version__.py
hexdoc_hyperhexcast/__init__.py
hexdoc_hyperhexcast/__version__.py
hexdoc_hyperhexcast/_hooks.py
hexdoc_hyperhexcast/py.typed
hexdoc_hyperhexcast/_export/.gitignore
hexdoc_hyperhexcast/_export/__init__.py
hexdoc_hyperhexcast/_export/generated/__init__.py
hexdoc_hyperhexcast/_export/generated/hyperhexcast.hexdoc.json
hexdoc_hyperhexcast/_export/generated/hyperhexcast.patterns.hexdoc.json
hexdoc_hyperhexcast/_export/generated/assets/hexcasting/patchouli_books/thehexbook/en_us/entries/patterns/mounts.json5
hexdoc_hyperhexcast/_export/generated/assets/hexcasting/patchouli_books/thehexbook/en_us/entries/patterns/spl_mounts.json5
hexdoc_hyperhexcast/_export/generated/assets/hexcasting/patchouli_books/thehexbook/en_us/entries/patterns/squareroot.json5
hexdoc_hyperhexcast/_export/generated/assets/hyperhexcast/lang/en_us.flatten.json5
hexdoc_hyperhexcast/_templates/__init__.py
hexdoc_hyperhexcast-0.1.1.1.0.dist-info/METADATA
hexdoc_hyperhexcast-0.1.1.1.0.dist-info/WHEEL
hexdoc_hyperhexcast-0.1.1.1.0.dist-info/entry_points.txt
hexdoc_hyperhexcast-0.1.1.1.0.dist-info/licenses/LICENSE
hexdoc_hyperhexcast-0.1.1.1.0.dist-info/RECORD
