Metadata-Version: 2.4
Name: hexdoc-hyperhexcast
Version: 0.1.1.1.0
Summary: Another HexCasting addon I guess
Project-URL: Homepage, https://janipen.github.io/hyper_hexcast
Project-URL: Source, https://github.com/janIpen/hyper_hexcast
Author: janIpen
License-File: LICENSE
Keywords: hexdoc
Requires-Python: >=3.12
Requires-Dist: hexdoc-hexcasting~=0.11.2.1.0
